parallel_websocket_server/__init__.py
parallel_websocket_server/server.py
parallel_websocket_server-0.1.3.dist-info/METADATA
parallel_websocket_server-0.1.3.dist-info/WHEEL
parallel_websocket_server-0.1.3.dist-info/RECORD
