Metadata-Version: 2.1
Name: parallel_websocket_server
Version: 0.1.3
Summary: python multiprocessing websocket server
Home-page: https://github.com/2ndr9/parallel_websocket_server
Author: 2ndr9
Requires-Python: >=3.9,<4.0
Classifier: Programming Language :: Python :: 3
Classifier: Programming Language :: Python :: 3.9
Classifier: Programming Language :: Python :: 3.10
Classifier: Programming Language :: Python :: 3.11
Requires-Dist: websockets (>=11.0.3,<12.0.0)
Project-URL: Repository, https://github.com/2ndr9/parallel_websocket_server
